[
  {
    "keyword": "innbrudd",
    "region": "NO",
    "started_at_unix": 1779004800,
    "ended_at_unix": null,
    "search_volume": 5000,
    "score": 1000,
    "related_queries": [
      "innbrudd"
    ],
    "category_ids": [
      10
    ],
    "entities": [
      {
        "id": 4608645498,
        "language": "en",
        "region": "NO"
      },
      {
        "id": 4607164476,
        "language": "en",
        "region": "NO"
      },
      {
        "id": 4608122555,
        "language": "en",
        "region": "NO"
      },
      {
        "id": 4606644403,
        "language": "en",
        "region": "NO"
      },
      {
        "id": 4591556988,
        "language": "en",
        "region": "NO"
      },
      {
        "id": 4604420976,
        "language": "en",
        "region": "NO"
      },
      {
        "id": 4603794089,
        "language": "en",
        "region": "NO"
      },
      {
        "id": 4602960252,
        "language": "en",
        "region": "NO"
      }
    ],
    "normalized_keyword": "innbrudd",
    "captured_at": "2026-05-18T06:59:34.801701+00:00"
  },
  {
    "keyword": "sverre magnus",
    "region": "NO",
    "started_at_unix": 1779006600,
    "ended_at_unix": null,
    "search_volume": 10000,
    "score": 1000,
    "related_queries": [
      "sverre magnus",
      "det norske kongehuset",
      "mette marit",
      "prins sverre magnus",
      "skaugum",
      "barnetoget",
      "når begynner barnetoget 17 mai",
      "barnetog oslo 17 mai"
    ],
    "category_ids": [
      10
    ],
    "entities": [
      {
        "id": 4587133547,
        "language": "en",
        "region": "NO"
      },
      {
        "id": 4587133547,
        "language": "de",
        "region": "NO"
      },
      {
        "id": 4607084073,
        "language": "de",
        "region": "NO"
      },
      {
        "id": 4608172007,
        "language": "en",
        "region": "NO"
      },
      {
        "id": 4607539689,
        "language": "en",
        "region": "NO"
      },
      {
        "id": 4587133547,
        "language": "no",
        "region": "NO"
      },
      {
        "id": 4607539676,
        "language": "no",
        "region": "NO"
      },
      {
        "id": 4603311932,
        "language": "no",
        "region": "NO"
      },
      {
        "id": 4597728728,
        "language": "no",
        "region": "NO"
      },
      {
        "id": 4599393194,
        "language": "no",
        "region": "NO"
      },
      {
        "id": 4607539676,
        "language": "en",
        "region": "NO"
      },
      {
        "id": 4607904688,
        "language": "en",
        "region": "NO"
      },
      {
        "id": 4607963810,
        "language": "en",
        "region": "NO"
      },
      {
        "id": 4606299412,
        "language": "en",
        "region": "NO"
      },
      {
        "id": 4607808636,
        "language": "en",
        "region": "NO"
      },
      {
        "id": 4607808600,
        "language": "en",
        "region": "NO"
      },
      {
        "id": 4588504636,
        "language": "en",
        "region": "NO"
      },
      {
        "id": 4588600195,
        "language": "en",
        "region": "NO"
      },
      {
        "id": 4607402519,
        "language": "en",
        "region": "NO"
      },
      {
        "id": 4607204549,
        "language": "en",
        "region": "NO"
      },
      {
        "id": 4595963390,
        "language": "en",
        "region": "NO"
      },
      {
        "id": 4607808632,
        "language": "en",
        "region": "NO"
      },
      {
        "id": 4608256113,
        "language": "en",
        "region": "NO"
      },
      {
        "id": 4607904670,
        "language": "en",
        "region": "NO"
      },
      {
        "id": 4606480279,
        "language": "en",
        "region": "NO"
      },
      {
        "id": 4607672414,
        "language": "en",
        "region": "NO"
      },
      {
        "id": 4607497628,
        "language": "en",
        "region": "NO"
      },
      {
        "id": 4608534882,
        "language": "en",
        "region": "NO"
      },
      {
        "id": 4607672392,
        "language": "en",
        "region": "NO"
      },
      {
        "id": 4604420923,
        "language": "en",
        "region": "NO"
      },
      {
        "id": 4589583571,
        "language": "en",
        "region": "NO"
      },
      {
        "id": 4608645524,
        "language": "en",
        "region": "NO"
      },
      {
        "id": 4590268562,
        "language": "en",
        "region": "NO"
      },
      {
        "id": 4567237298,
        "language": "en",
        "region": "NO"
      },
      {
        "id": 4512063041,
        "language": "en",
        "region": "NO"
      },
      {
        "id": 4588504636,
        "language": "no",
        "region": "NO"
      }
    ],
    "normalized_keyword": "sverre magnus",
    "captured_at": "2026-05-18T06:59:34.801701+00:00"
  },
  {
    "keyword": "rosenborg ballklub",
    "region": "NO",
    "started_at_unix": 1779048000,
    "ended_at_unix": null,
    "search_volume": 1000,
    "score": 700,
    "related_queries": [
      "rosenborg ballklub"
    ],
    "category_ids": [
      17
    ],
    "entities": [
      {
        "id": 4606441566,
        "language": "en",
        "region": "NO"
      },
      {
        "id": 4606354492,
        "language": "en",
        "region": "NO"
      },
      {
        "id": 4599245298,
        "language": "en",
        "region": "NO"
      },
      {
        "id": 4604374747,
        "language": "en",
        "region": "NO"
      },
      {
        "id": 4603607135,
        "language": "en",
        "region": "NO"
      },
      {
        "id": 4578808335,
        "language": "en",
        "region": "NO"
      }
    ],
    "normalized_keyword": "rosenborg ballklub",
    "captured_at": "2026-05-18T06:59:34.801701+00:00"
  },
  {
    "keyword": "barcelona mot real betis",
    "region": "NO",
    "started_at_unix": 1779042600,
    "ended_at_unix": null,
    "search_volume": 2000,
    "score": 1000,
    "related_queries": [
      "barcelona mot real betis"
    ],
    "category_ids": [
      17
    ],
    "entities": [
      {
        "id": 4579151483,
        "language": "en",
        "region": "US"
      },
      {
        "id": 4579502547,
        "language": "en",
        "region": "US"
      }
    ],
    "normalized_keyword": "barcelona mot real betis",
    "captured_at": "2026-05-18T06:59:34.801701+00:00"
  },
  {
    "keyword": "usa",
    "region": "NO",
    "started_at_unix": 1779075600,
    "ended_at_unix": null,
    "search_volume": 500,
    "score": 700,
    "related_queries": [
      "usa"
    ],
    "category_ids": [
      10,
      14
    ],
    "entities": [
      {
        "id": 4606922099,
        "language": "en",
        "region": "NO"
      },
      {
        "id": 4601579546,
        "language": "en",
        "region": "NO"
      },
      {
        "id": 4591190437,
        "language": "en",
        "region": "NO"
      },
      {
        "id": 4608403733,
        "language": "en",
        "region": "NO"
      },
      {
        "id": 4590643715,
        "language": "en",
        "region": "NO"
      },
      {
        "id": 4603382411,
        "language": "en",
        "region": "NO"
      },
      {
        "id": 4608403735,
        "language": "en",
        "region": "NO"
      },
      {
        "id": 4607904664,
        "language": "en",
        "region": "NO"
      },
      {
        "id": 4597728690,
        "language": "en",
        "region": "NO"
      }
    ],
    "normalized_keyword": "usa",
    "captured_at": "2026-05-18T06:59:34.801701+00:00"
  },
  {
    "keyword": "eksplosjon",
    "region": "NO",
    "started_at_unix": 1779023400,
    "ended_at_unix": null,
    "search_volume": 1000,
    "score": 1000,
    "related_queries": [
      "eksplosjon"
    ],
    "category_ids": [
      8
    ],
    "entities": [
      {
        "id": 4607625830,
        "language": "en",
        "region": "NO"
      }
    ],
    "normalized_keyword": "eksplosjon",
    "captured_at": "2026-05-18T06:59:34.801701+00:00"
  },
  {
    "keyword": "nittedal",
    "region": "NO",
    "started_at_unix": 1779042600,
    "ended_at_unix": null,
    "search_volume": 1000,
    "score": 1000,
    "related_queries": [
      "nittedal"
    ],
    "category_ids": [
      11
    ],
    "entities": [
      {
        "id": 4599697428,
        "language": "en",
        "region": "NO"
      }
    ],
    "normalized_keyword": "nittedal",
    "captured_at": "2026-05-18T06:59:34.801701+00:00"
  },
  {
    "keyword": "australia",
    "region": "NO",
    "started_at_unix": 1779025200,
    "ended_at_unix": null,
    "search_volume": 500,
    "score": 700,
    "related_queries": [
      "australia"
    ],
    "category_ids": [
      3
    ],
    "entities": [
      {
        "id": 4600257339,
        "language": "en",
        "region": "NO"
      },
      {
        "id": 4588453003,
        "language": "en",
        "region": "NO"
      },
      {
        "id": 4605105769,
        "language": "en",
        "region": "NO"
      },
      {
        "id": 4597709956,
        "language": "en",
        "region": "NO"
      },
      {
        "id": 4596930295,
        "language": "en",
        "region": "NO"
      },
      {
        "id": 4608992393,
        "language": "en",
        "region": "NO"
      },
      {
        "id": 4608981142,
        "language": "en",
        "region": "NO"
      },
      {
        "id": 4608567353,
        "language": "en",
        "region": "NO"
      }
    ],
    "normalized_keyword": "australia",
    "captured_at": "2026-05-18T06:59:34.801701+00:00"
  },
  {
    "keyword": "varingen",
    "region": "NO",
    "started_at_unix": 1779040200,
    "ended_at_unix": null,
    "search_volume": 500,
    "score": 800,
    "related_queries": [
      "varingen"
    ],
    "category_ids": [
      11
    ],
    "entities": [
      {
        "id": 4608012365,
        "language": "en",
        "region": "NO"
      },
      {
        "id": 4599697428,
        "language": "en",
        "region": "NO"
      },
      {
        "id": 4608403773,
        "language": "en",
        "region": "NO"
      }
    ],
    "normalized_keyword": "varingen",
    "captured_at": "2026-05-18T06:59:34.801701+00:00"
  },
  {
    "keyword": "man. united mot nottingham forest",
    "region": "NO",
    "started_at_unix": 1779014400,
    "ended_at_unix": 1779076200,
    "search_volume": 10000,
    "score": 1000,
    "related_queries": [
      "man. united mot nottingham forest"
    ],
    "category_ids": [
      17
    ],
    "entities": [
      {
        "id": 4607848574,
        "language": "en",
        "region": "NO"
      },
      {
        "id": 4607848624,
        "language": "en",
        "region": "NO"
      },
      {
        "id": 4596657609,
        "language": "en",
        "region": "NO"
      }
    ],
    "normalized_keyword": "man. united mot nottingham forest",
    "captured_at": "2026-05-18T06:59:34.801701+00:00"
  },
  {
    "keyword": "donald trump",
    "region": "NO",
    "started_at_unix": 1779038400,
    "ended_at_unix": 1779084600,
    "search_volume": 2000,
    "score": 1000,
    "related_queries": [
      "donald trump"
    ],
    "category_ids": [
      14
    ],
    "entities": [
      {
        "id": 4564660264,
        "language": "en",
        "region": "NO"
      },
      {
        "id": 4592410302,
        "language": "en",
        "region": "NO"
      },
      {
        "id": 4591190437,
        "language": "en",
        "region": "NO"
      },
      {
        "id": 4605418811,
        "language": "en",
        "region": "NO"
      },
      {
        "id": 4581416091,
        "language": "en",
        "region": "NO"
      },
      {
        "id": 4588456967,
        "language": "en",
        "region": "NO"
      },
      {
        "id": 4597788181,
        "language": "en",
        "region": "NO"
      },
      {
        "id": 4550086705,
        "language": "en",
        "region": "NO"
      },
      {
        "id": 4605943113,
        "language": "en",
        "region": "NO"
      },
      {
        "id": 4605014479,
        "language": "en",
        "region": "NO"
      }
    ],
    "normalized_keyword": "donald trump",
    "captured_at": "2026-05-18T06:59:34.801701+00:00"
  },
  {
    "keyword": "bergensavisen",
    "region": "NO",
    "started_at_unix": 1779001800,
    "ended_at_unix": 1779085200,
    "search_volume": 2000,
    "score": 1000,
    "related_queries": [
      "bergensavisen",
      "bergen"
    ],
    "category_ids": [
      20,
      8,
      19
    ],
    "entities": [
      {
        "id": 4608977675,
        "language": "en",
        "region": "NO"
      },
      {
        "id": 4607723637,
        "language": "en",
        "region": "NO"
      },
      {
        "id": 4608122578,
        "language": "en",
        "region": "NO"
      },
      {
        "id": 4608828981,
        "language": "en",
        "region": "NO"
      },
      {
        "id": 4599282160,
        "language": "en",
        "region": "NO"
      },
      {
        "id": 4606530256,
        "language": "en",
        "region": "NO"
      },
      {
        "id": 4607307465,
        "language": "en",
        "region": "NO"
      },
      {
        "id": 4605782464,
        "language": "en",
        "region": "NO"
      },
      {
        "id": 4609011963,
        "language": "en",
        "region": "NO"
      },
      {
        "id": 4608340751,
        "language": "en",
        "region": "NO"
      },
      {
        "id": 4608340705,
        "language": "en",
        "region": "NO"
      },
      {
        "id": 4608288415,
        "language": "en",
        "region": "NO"
      },
      {
        "id": 4608256111,
        "language": "en",
        "region": "NO"
      }
    ],
    "normalized_keyword": "bergensavisen",
    "captured_at": "2026-05-18T06:59:34.801701+00:00"
  },
  {
    "keyword": "fc barcelona – real betis",
    "region": "NO",
    "started_at_unix": 1779044400,
    "ended_at_unix": 1779083400,
    "search_volume": 1000,
    "score": 1000,
    "related_queries": [
      "fc barcelona – real betis",
      "barcelona vs real betis"
    ],
    "category_ids": [
      17
    ],
    "entities": [
      {
        "id": 4601616321,
        "language": "es",
        "region": "NO"
      },
      {
        "id": 4606748463,
        "language": "es",
        "region": "NO"
      }
    ],
    "normalized_keyword": "fc barcelona – real betis",
    "captured_at": "2026-05-18T06:59:34.801701+00:00"
  },
  {
    "keyword": "dennis locorriere",
    "region": "NO",
    "started_at_unix": 1779036000,
    "ended_at_unix": 1779086400,
    "search_volume": 2000,
    "score": 1000,
    "related_queries": [
      "dennis locorriere",
      "dr hook"
    ],
    "category_ids": [
      4
    ],
    "entities": [
      {
        "id": 4607673778,
        "language": "en",
        "region": "US"
      },
      {
        "id": 4607673778,
        "language": "en",
        "region": "NO"
      }
    ],
    "normalized_keyword": "dennis locorriere",
    "captured_at": "2026-05-18T06:59:34.801701+00:00"
  },
  {
    "keyword": "helikopter",
    "region": "NO",
    "started_at_unix": 1779028800,
    "ended_at_unix": 1779082200,
    "search_volume": 1000,
    "score": 1000,
    "related_queries": [
      "helikopter"
    ],
    "category_ids": [
      10
    ],
    "entities": [
      {
        "id": 4607771744,
        "language": "en",
        "region": "NO"
      },
      {
        "id": 4606390911,
        "language": "en",
        "region": "NO"
      },
      {
        "id": 4588555181,
        "language": "en",
        "region": "NO"
      }
    ],
    "normalized_keyword": "helikopter",
    "captured_at": "2026-05-18T06:59:34.801701+00:00"
  },
  {
    "keyword": "josé mourinho",
    "region": "NO",
    "started_at_unix": 1779039600,
    "ended_at_unix": 1779083400,
    "search_volume": 500,
    "score": 600,
    "related_queries": [
      "josé mourinho"
    ],
    "category_ids": [
      17
    ],
    "entities": [
      {
        "id": 4608903238,
        "language": "en",
        "region": "NO"
      },
      {
        "id": 4597952844,
        "language": "en",
        "region": "NO"
      },
      {
        "id": 4580490260,
        "language": "en",
        "region": "NO"
      },
      {
        "id": 4588456828,
        "language": "en",
        "region": "NO"
      },
      {
        "id": 4603117450,
        "language": "en",
        "region": "NO"
      }
    ],
    "normalized_keyword": "jose mourinho",
    "captured_at": "2026-05-18T06:59:34.801701+00:00"
  },
  {
    "keyword": "newcastle mot west ham",
    "region": "NO",
    "started_at_unix": 1779033000,
    "ended_at_unix": 1779049800,
    "search_volume": 2000,
    "score": 1000,
    "related_queries": [
      "newcastle mot west ham"
    ],
    "category_ids": [
      17
    ],
    "entities": [
      {
        "id": 4603569894,
        "language": "en",
        "region": "NO"
      }
    ],
    "normalized_keyword": "newcastle mot west ham",
    "captured_at": "2026-05-18T06:59:34.801701+00:00"
  },
  {
    "keyword": "kong harald",
    "region": "NO",
    "started_at_unix": 1779006600,
    "ended_at_unix": 1779033600,
    "search_volume": 2000,
    "score": 1000,
    "related_queries": [
      "kong harald"
    ],
    "category_ids": [
      8,
      16
    ],
    "entities": [
      {
        "id": 4607577134,
        "language": "en",
        "region": "NO"
      },
      {
        "id": 4587133547,
        "language": "en",
        "region": "NO"
      },
      {
        "id": 4599393194,
        "language": "en",
        "region": "NO"
      },
      {
        "id": 4596904355,
        "language": "en",
        "region": "NO"
      },
      {
        "id": 4607539676,
        "language": "en",
        "region": "NO"
      },
      {
        "id": 4603311932,
        "language": "en",
        "region": "NO"
      }
    ],
    "normalized_keyword": "kong harald",
    "captured_at": "2026-05-18T06:59:34.801701+00:00"
  },
  {
    "keyword": "fotballklubben bodø/glimt",
    "region": "NO",
    "started_at_unix": 1779009600,
    "ended_at_unix": 1779043200,
    "search_volume": 1000,
    "score": 1000,
    "related_queries": [
      "fotballklubben bodø/glimt"
    ],
    "category_ids": [
      17
    ],
    "entities": [
      {
        "id": 4593718043,
        "language": "en",
        "region": "NO"
      },
      {
        "id": 4601723790,
        "language": "en",
        "region": "NO"
      },
      {
        "id": 4602318861,
        "language": "en",
        "region": "NO"
      }
    ],
    "normalized_keyword": "fotballklubben bodø/glimt",
    "captured_at": "2026-05-18T06:59:34.801701+00:00"
  },
  {
    "keyword": "awacs",
    "region": "NO",
    "started_at_unix": 1779026400,
    "ended_at_unix": 1779078000,
    "search_volume": 500,
    "score": 1000,
    "related_queries": [
      "awacs"
    ],
    "category_ids": [
      10,
      3,
      14
    ],
    "entities": [
      {
        "id": 4603977333,
        "language": "en",
        "region": "NO"
      },
      {
        "id": 4599794622,
        "language": "en",
        "region": "NO"
      },
      {
        "id": 4557546082,
        "language": "en",
        "region": "NO"
      }
    ],
    "normalized_keyword": "awacs",
    "captured_at": "2026-05-18T06:59:34.801701+00:00"
  },
  {
    "keyword": "man united vs nottm forest",
    "region": "NO",
    "started_at_unix": 1779015600,
    "ended_at_unix": 1779029400,
    "search_volume": 2000,
    "score": 1000,
    "related_queries": [
      "man united vs nottm forest",
      "manchester united",
      "united",
      "bruno fernandes",
      "man utd"
    ],
    "category_ids": [
      17
    ],
    "entities": [
      {
        "id": 4599735512,
        "language": "en",
        "region": "NO"
      },
      {
        "id": 4599075918,
        "language": "en",
        "region": "NO"
      },
      {
        "id": 4607830433,
        "language": "en",
        "region": "NO"
      },
      {
        "id": 4583261387,
        "language": "en",
        "region": "NO"
      },
      {
        "id": 4608099936,
        "language": "en",
        "region": "NO"
      },
      {
        "id": 4603001652,
        "language": "en",
        "region": "NO"
      },
      {
        "id": 4583807469,
        "language": "en",
        "region": "NO"
      },
      {
        "id": 4581002734,
        "language": "en",
        "region": "NO"
      },
      {
        "id": 4607630710,
        "language": "en",
        "region": "NO"
      },
      {
        "id": 4599477094,
        "language": "en",
        "region": "NO"
      },
      {
        "id": 4603450185,
        "language": "en",
        "region": "NO"
      },
      {
        "id": 4607848574,
        "language": "en",
        "region": "NO"
      },
      {
        "id": 4608271103,
        "language": "en",
        "region": "NO"
      },
      {
        "id": 4607539640,
        "language": "en",
        "region": "NO"
      },
      {
        "id": 4593830456,
        "language": "en",
        "region": "NO"
      },
      {
        "id": 4568035565,
        "language": "en",
        "region": "NO"
      }
    ],
    "normalized_keyword": "man united vs nottm forest",
    "captured_at": "2026-05-18T06:59:34.801701+00:00"
  },
  {
    "keyword": "casper ruud",
    "region": "NO",
    "started_at_unix": 1779031800,
    "ended_at_unix": 1779042000,
    "search_volume": 2000,
    "score": 700,
    "related_queries": [
      "casper ruud",
      "sinner"
    ],
    "category_ids": [
      17
    ],
    "entities": [
      {
        "id": 4607390672,
        "language": "en",
        "region": "NO"
      },
      {
        "id": 4605437624,
        "language": "en",
        "region": "NO"
      },
      {
        "id": 4584968394,
        "language": "en",
        "region": "NO"
      },
      {
        "id": 4608105826,
        "language": "en",
        "region": "NO"
      },
      {
        "id": 4583718152,
        "language": "en",
        "region": "NO"
      },
      {
        "id": 4608438985,
        "language": "en",
        "region": "NO"
      }
    ],
    "normalized_keyword": "casper ruud",
    "captured_at": "2026-05-18T06:59:34.801701+00:00"
  },
  {
    "keyword": "tvangssalg",
    "region": "NO",
    "started_at_unix": 1779006600,
    "ended_at_unix": 1779058200,
    "search_volume": 1000,
    "score": 1000,
    "related_queries": [
      "tvangssalg"
    ],
    "category_ids": [
      3,
      10
    ],
    "entities": [
      {
        "id": 4606872917,
        "language": "en",
        "region": "NO"
      },
      {
        "id": 4605909877,
        "language": "en",
        "region": "NO"
      },
      {
        "id": 4604607434,
        "language": "en",
        "region": "NO"
      }
    ],
    "normalized_keyword": "tvangssalg",
    "captured_at": "2026-05-18T06:59:34.801701+00:00"
  },
  {
    "keyword": "aaron rai",
    "region": "NO",
    "started_at_unix": 1779058200,
    "ended_at_unix": 1779085200,
    "search_volume": 200,
    "score": 300,
    "related_queries": [
      "aaron rai",
      "pga"
    ],
    "category_ids": [
      17
    ],
    "entities": [
      {
        "id": 4606665308,
        "language": "en",
        "region": "NO"
      },
      {
        "id": 4603038295,
        "language": "en",
        "region": "NO"
      },
      {
        "id": 4608544306,
        "language": "en",
        "region": "NO"
      },
      {
        "id": 4596058559,
        "language": "en",
        "region": "NO"
      },
      {
        "id": 4578969070,
        "language": "en",
        "region": "NO"
      },
      {
        "id": 4606904536,
        "language": "en",
        "region": "NO"
      }
    ],
    "normalized_keyword": "aaron rai",
    "captured_at": "2026-05-18T06:59:34.801701+00:00"
  },
  {
    "keyword": "ebola virus",
    "region": "NO",
    "started_at_unix": 1779004200,
    "ended_at_unix": 1779086400,
    "search_volume": 500,
    "score": 1000,
    "related_queries": [
      "ebola virus"
    ],
    "category_ids": [
      7,
      10
    ],
    "entities": [
      {
        "id": 4603097471,
        "language": "en",
        "region": "NO"
      }
    ],
    "normalized_keyword": "ebola virus",
    "captured_at": "2026-05-18T06:59:34.801701+00:00"
  },
  {
    "keyword": "stephen graham",
    "region": "NO",
    "started_at_unix": 1779052800,
    "ended_at_unix": 1779067800,
    "search_volume": 200,
    "score": 1000,
    "related_queries": [
      "stephen graham"
    ],
    "category_ids": [
      4
    ],
    "entities": [
      {
        "id": 4608288472,
        "language": "en",
        "region": "NO"
      },
      {
        "id": 4600070833,
        "language": "en",
        "region": "NO"
      },
      {
        "id": 4574055546,
        "language": "en",
        "region": "NO"
      }
    ],
    "normalized_keyword": "stephen graham",
    "captured_at": "2026-05-18T06:59:34.801701+00:00"
  },
  {
    "keyword": "borgertoget kristiansand",
    "region": "NO",
    "started_at_unix": 1779016800,
    "ended_at_unix": 1779033600,
    "search_volume": 1000,
    "score": 1000,
    "related_queries": [
      "borgertoget kristiansand",
      "borgertoget kristiansand 2026"
    ],
    "category_ids": [
      11
    ],
    "entities": [
      {
        "id": 4599444099,
        "language": "en",
        "region": "NO"
      }
    ],
    "normalized_keyword": "borgertoget kristiansand",
    "captured_at": "2026-05-18T06:59:34.801701+00:00"
  },
  {
    "keyword": "n",
    "region": "NO",
    "started_at_unix": 1779076800,
    "ended_at_unix": 1779083400,
    "search_volume": 100,
    "score": 100,
    "related_queries": [
      "n"
    ],
    "category_ids": [
      16,
      3
    ],
    "entities": [
      {
        "id": 4608288449,
        "language": "en",
        "region": "NO"
      },
      {
        "id": 4608403784,
        "language": "en",
        "region": "NO"
      },
      {
        "id": 4608700386,
        "language": "en",
        "region": "NO"
      }
    ],
    "normalized_keyword": "n",
    "captured_at": "2026-05-18T06:59:34.801701+00:00"
  },
  {
    "keyword": "ea-18g growler",
    "region": "NO",
    "started_at_unix": 1779052800,
    "ended_at_unix": 1779081000,
    "search_volume": 200,
    "score": 800,
    "related_queries": [
      "ea-18g growler"
    ],
    "category_ids": [
      10
    ],
    "entities": [
      {
        "id": 4608237419,
        "language": "en",
        "region": "US"
      }
    ],
    "normalized_keyword": "ea-18g growler",
    "captured_at": "2026-05-18T06:59:34.801701+00:00"
  },
  {
    "keyword": "ishockey vm",
    "region": "NO",
    "started_at_unix": 1779048600,
    "ended_at_unix": 1779081600,
    "search_volume": 200,
    "score": 200,
    "related_queries": [
      "ishockey vm"
    ],
    "category_ids": [
      17
    ],
    "entities": [
      {
        "id": 4608344662,
        "language": "sv",
        "region": "NO"
      },
      {
        "id": 4606144405,
        "language": "sv",
        "region": "NO"
      },
      {
        "id": 4608202023,
        "language": "sv",
        "region": "NO"
      },
      {
        "id": 4608288499,
        "language": "sv",
        "region": "NO"
      },
      {
        "id": 4606724433,
        "language": "sv",
        "region": "NO"
      },
      {
        "id": 4594920160,
        "language": "sv",
        "region": "NO"
      }
    ],
    "normalized_keyword": "ishockey vm",
    "captured_at": "2026-05-18T06:59:34.801701+00:00"
  },
  {
    "keyword": "buss",
    "region": "NO",
    "started_at_unix": 1779016200,
    "ended_at_unix": 1779037800,
    "search_volume": 500,
    "score": 1000,
    "related_queries": [
      "buss"
    ],
    "category_ids": [
      11
    ],
    "entities": [
      {
        "id": 4607204563,
        "language": "en",
        "region": "NO"
      },
      {
        "id": 4606745551,
        "language": "en",
        "region": "NO"
      },
      {
        "id": 4604885703,
        "language": "en",
        "region": "NO"
      },
      {
        "id": 4608929386,
        "language": "en",
        "region": "NO"
      },
      {
        "id": 4604089963,
        "language": "en",
        "region": "NO"
      },
      {
        "id": 4597855956,
        "language": "en",
        "region": "NO"
      },
      {
        "id": 4608700408,
        "language": "en",
        "region": "NO"
      },
      {
        "id": 4608067985,
        "language": "en",
        "region": "NO"
      },
      {
        "id": 4606354445,
        "language": "en",
        "region": "NO"
      },
      {
        "id": 4539111406,
        "language": "en",
        "region": "NO"
      }
    ],
    "normalized_keyword": "buss",
    "captured_at": "2026-05-18T06:59:34.801701+00:00"
  },
  {
    "keyword": "bergens tidende",
    "region": "NO",
    "started_at_unix": 1779029400,
    "ended_at_unix": 1779044400,
    "search_volume": 500,
    "score": 500,
    "related_queries": [
      "bergens tidende"
    ],
    "category_ids": [
      11
    ],
    "entities": [
      {
        "id": 4597099587,
        "language": "en",
        "region": "NO"
      },
      {
        "id": 4594062984,
        "language": "en",
        "region": "NO"
      },
      {
        "id": 4608782843,
        "language": "en",
        "region": "NO"
      },
      {
        "id": 4564012515,
        "language": "en",
        "region": "NO"
      }
    ],
    "normalized_keyword": "bergens tidende",
    "captured_at": "2026-05-18T06:59:34.801701+00:00"
  },
  {
    "keyword": "jannik sinner",
    "region": "NO",
    "started_at_unix": 1779031200,
    "ended_at_unix": 1779042600,
    "search_volume": 500,
    "score": 1000,
    "related_queries": [
      "jannik sinner"
    ],
    "category_ids": [
      17
    ],
    "entities": [
      {
        "id": 4608146867,
        "language": "it",
        "region": "NO"
      },
      {
        "id": 4587918997,
        "language": "it",
        "region": "NO"
      },
      {
        "id": 4607762359,
        "language": "it",
        "region": "NO"
      },
      {
        "id": 4592963464,
        "language": "it",
        "region": "NO"
      },
      {
        "id": 4583001988,
        "language": "it",
        "region": "NO"
      },
      {
        "id": 4584968394,
        "language": "it",
        "region": "NO"
      },
      {
        "id": 4583965339,
        "language": "it",
        "region": "NO"
      }
    ],
    "normalized_keyword": "jannik sinner",
    "captured_at": "2026-05-18T06:59:34.801701+00:00"
  },
  {
    "keyword": "politiloggen",
    "region": "NO",
    "started_at_unix": 1779058200,
    "ended_at_unix": 1779073200,
    "search_volume": 200,
    "score": 200,
    "related_queries": [
      "politiloggen"
    ],
    "category_ids": [
      10
    ],
    "entities": [
      {
        "id": 4607723637,
        "language": "en",
        "region": "NO"
      },
      {
        "id": 4604607435,
        "language": "en",
        "region": "NO"
      }
    ],
    "normalized_keyword": "politiloggen",
    "captured_at": "2026-05-18T06:59:34.801701+00:00"
  },
  {
    "keyword": "jan mayen",
    "region": "NO",
    "started_at_unix": 1779015600,
    "ended_at_unix": 1779047400,
    "search_volume": 1000,
    "score": 1000,
    "related_queries": [
      "jan mayen"
    ],
    "category_ids": [
      10,
      3
    ],
    "entities": [
      {
        "id": 4603041080,
        "language": "en",
        "region": "NO"
      }
    ],
    "normalized_keyword": "jan mayen",
    "captured_at": "2026-05-18T06:59:34.801701+00:00"
  },
  {
    "keyword": "rb",
    "region": "NO",
    "started_at_unix": 1779040200,
    "ended_at_unix": 1779087600,
    "search_volume": 200,
    "score": 100,
    "related_queries": [
      "rb"
    ],
    "category_ids": [
      17
    ],
    "entities": [
      {
        "id": 4568994277,
        "language": "en",
        "region": "US"
      },
      {
        "id": 4599580449,
        "language": "en",
        "region": "US"
      },
      {
        "id": 4608541306,
        "language": "en",
        "region": "US"
      },
      {
        "id": 4606788977,
        "language": "en",
        "region": "US"
      },
      {
        "id": 4593477316,
        "language": "en",
        "region": "US"
      },
      {
        "id": 4595134565,
        "language": "en",
        "region": "US"
      },
      {
        "id": 4588415343,
        "language": "en",
        "region": "US"
      },
      {
        "id": 4566206735,
        "language": "en",
        "region": "US"
      },
      {
        "id": 4517593011,
        "language": "en",
        "region": "US"
      }
    ],
    "normalized_keyword": "rb",
    "captured_at": "2026-05-18T06:59:34.801701+00:00"
  },
  {
    "keyword": "cher",
    "region": "NO",
    "started_at_unix": 1779052200,
    "ended_at_unix": 1779058200,
    "search_volume": 200,
    "score": 1000,
    "related_queries": [
      "cher"
    ],
    "category_ids": [
      4
    ],
    "entities": [
      {
        "id": 4608512627,
        "language": "en",
        "region": "US"
      },
      {
        "id": 4596224890,
        "language": "en",
        "region": "US"
      },
      {
        "id": 4607907030,
        "language": "en",
        "region": "US"
      },
      {
        "id": 4604176312,
        "language": "en",
        "region": "US"
      },
      {
        "id": 4607549101,
        "language": "en",
        "region": "US"
      },
      {
        "id": 4604359669,
        "language": "en",
        "region": "US"
      },
      {
        "id": 4542590585,
        "language": "en",
        "region": "US"
      },
      {
        "id": 4545995631,
        "language": "en",
        "region": "US"
      }
    ],
    "normalized_keyword": "cher",
    "captured_at": "2026-05-18T06:59:34.801701+00:00"
  },
  {
    "keyword": "kjetil knutsen",
    "region": "NO",
    "started_at_unix": 1779045000,
    "ended_at_unix": 1779081000,
    "search_volume": 200,
    "score": 1000,
    "related_queries": [
      "kjetil knutsen"
    ],
    "category_ids": [
      17
    ],
    "entities": [
      {
        "id": 4602318861,
        "language": "en",
        "region": "NO"
      },
      {
        "id": 4606441578,
        "language": "en",
        "region": "NO"
      },
      {
        "id": 4601723790,
        "language": "en",
        "region": "NO"
      }
    ],
    "normalized_keyword": "kjetil knutsen",
    "captured_at": "2026-05-18T06:59:34.801701+00:00"
  },
  {
    "keyword": "stavanger aftenblad",
    "region": "NO",
    "started_at_unix": 1779080400,
    "ended_at_unix": 1779084000,
    "search_volume": 100,
    "score": 50,
    "related_queries": [
      "stavanger aftenblad"
    ],
    "category_ids": [
      11
    ],
    "entities": [
      {
        "id": 4608828985,
        "language": "en",
        "region": "NO"
      },
      {
        "id": 4608012428,
        "language": "en",
        "region": "NO"
      }
    ],
    "normalized_keyword": "stavanger aftenblad",
    "captured_at": "2026-05-18T06:59:34.801701+00:00"
  },
  {
    "keyword": "dronning sonja",
    "region": "NO",
    "started_at_unix": 1779007200,
    "ended_at_unix": 1779022800,
    "search_volume": 500,
    "score": 1000,
    "related_queries": [
      "dronning sonja"
    ],
    "category_ids": [
      10,
      4
    ],
    "entities": [
      {
        "id": 4605782449,
        "language": "en",
        "region": "NO"
      },
      {
        "id": 4597728728,
        "language": "en",
        "region": "NO"
      },
      {
        "id": 4587133547,
        "language": "en",
        "region": "NO"
      },
      {
        "id": 4601723834,
        "language": "en",
        "region": "NO"
      }
    ],
    "normalized_keyword": "dronning sonja",
    "captured_at": "2026-05-18T06:59:34.801701+00:00"
  },
  {
    "keyword": "sevilla vs real madrid",
    "region": "NO",
    "started_at_unix": 1779039000,
    "ended_at_unix": 1779048600,
    "search_volume": 200,
    "score": 800,
    "related_queries": [
      "sevilla vs real madrid"
    ],
    "category_ids": [
      17
    ],
    "entities": [
      {
        "id": 4601939939,
        "language": "en",
        "region": "NO"
      },
      {
        "id": 4605802645,
        "language": "en",
        "region": "NO"
      },
      {
        "id": 4602436879,
        "language": "en",
        "region": "NO"
      }
    ],
    "normalized_keyword": "sevilla vs real madrid",
    "captured_at": "2026-05-18T06:59:34.801701+00:00"
  },
  {
    "keyword": "bryne",
    "region": "NO",
    "started_at_unix": 1779051000,
    "ended_at_unix": 1779085200,
    "search_volume": 100,
    "score": 400,
    "related_queries": [
      "bryne"
    ],
    "category_ids": [
      17
    ],
    "entities": [
      {
        "id": 4588061651,
        "language": "en",
        "region": "US"
      },
      {
        "id": 4607611708,
        "language": "en",
        "region": "US"
      }
    ],
    "normalized_keyword": "bryne",
    "captured_at": "2026-05-18T06:59:34.801701+00:00"
  },
  {
    "keyword": "17 mai trondheim",
    "region": "NO",
    "started_at_unix": 1779003600,
    "ended_at_unix": 1779019200,
    "search_volume": 500,
    "score": 600,
    "related_queries": [
      "17 mai trondheim",
      "17 mai tog trondheim",
      "folketoget",
      "trondheim 17 mai"
    ],
    "category_ids": [
      11
    ],
    "entities": [
      {
        "id": 4608340680,
        "language": "en",
        "region": "NO"
      },
      {
        "id": 4608012423,
        "language": "en",
        "region": "NO"
      },
      {
        "id": 4608216598,
        "language": "en",
        "region": "NO"
      },
      {
        "id": 4608012389,
        "language": "en",
        "region": "NO"
      },
      {
        "id": 4607307522,
        "language": "en",
        "region": "NO"
      },
      {
        "id": 4608340728,
        "language": "en",
        "region": "NO"
      },
      {
        "id": 4607672392,
        "language": "en",
        "region": "NO"
      },
      {
        "id": 4602960222,
        "language": "en",
        "region": "NO"
      },
      {
        "id": 4608340680,
        "language": "de",
        "region": "NO"
      },
      {
        "id": 4608288448,
        "language": "de",
        "region": "NO"
      },
      {
        "id": 4606987831,
        "language": "de",
        "region": "NO"
      },
      {
        "id": 4596989950,
        "language": "de",
        "region": "NO"
      },
      {
        "id": 4551071098,
        "language": "de",
        "region": "NO"
      },
      {
        "id": 4596989950,
        "language": "en",
        "region": "NO"
      },
      {
        "id": 4608256206,
        "language": "de",
        "region": "NO"
      },
      {
        "id": 4607963776,
        "language": "de",
        "region": "NO"
      }
    ],
    "normalized_keyword": "17 mai trondheim",
    "captured_at": "2026-05-18T06:59:34.801701+00:00"
  },
  {
    "keyword": "ingrid alexandra",
    "region": "NO",
    "started_at_unix": 1779007200,
    "ended_at_unix": 1779022200,
    "search_volume": 200,
    "score": 1000,
    "related_queries": [
      "ingrid alexandra"
    ],
    "category_ids": [
      10
    ],
    "entities": [
      {
        "id": 4607539676,
        "language": "en",
        "region": "NO"
      },
      {
        "id": 4587133547,
        "language": "en",
        "region": "NO"
      },
      {
        "id": 4590268562,
        "language": "en",
        "region": "NO"
      },
      {
        "id": 4607723687,
        "language": "en",
        "region": "NO"
      }
    ],
    "normalized_keyword": "ingrid alexandra",
    "captured_at": "2026-05-18T06:59:34.801701+00:00"
  },
  {
    "keyword": "borgertoget bodø",
    "region": "NO",
    "started_at_unix": 1779019800,
    "ended_at_unix": 1779030000,
    "search_volume": 200,
    "score": 1000,
    "related_queries": [
      "borgertoget bodø",
      "17"
    ],
    "category_ids": [
      17
    ],
    "entities": [
      {
        "id": 4601723790,
        "language": "en",
        "region": "NO"
      },
      {
        "id": 4606480289,
        "language": "en",
        "region": "NO"
      },
      {
        "id": 4606480279,
        "language": "en",
        "region": "NO"
      },
      {
        "id": 4593163088,
        "language": "en",
        "region": "NO"
      },
      {
        "id": 4608122564,
        "language": "en",
        "region": "NO"
      },
      {
        "id": 4587133547,
        "language": "en",
        "region": "NO"
      },
      {
        "id": 4607723637,
        "language": "en",
        "region": "NO"
      },
      {
        "id": 4604936183,
        "language": "en",
        "region": "NO"
      },
      {
        "id": 4599697454,
        "language": "en",
        "region": "NO"
      },
      {
        "id": 4607497628,
        "language": "en",
        "region": "NO"
      }
    ],
    "normalized_keyword": "borgertoget bodø",
    "captured_at": "2026-05-18T06:59:34.801701+00:00"
  },
  {
    "keyword": "newcastle vs west ham",
    "region": "NO",
    "started_at_unix": 1779039000,
    "ended_at_unix": 1779045000,
    "search_volume": 200,
    "score": 1000,
    "related_queries": [
      "newcastle vs west ham"
    ],
    "category_ids": [
      17
    ],
    "entities": [
      {
        "id": 4583807469,
        "language": "en",
        "region": "NO"
      },
      {
        "id": 4608417377,
        "language": "en",
        "region": "NO"
      }
    ],
    "normalized_keyword": "newcastle vs west ham",
    "captured_at": "2026-05-18T06:59:34.801701+00:00"
  },
  {
    "keyword": "17.mai 2026",
    "region": "NO",
    "started_at_unix": 1779002400,
    "ended_at_unix": 1779015000,
    "search_volume": 200,
    "score": 500,
    "related_queries": [
      "17.mai 2026"
    ],
    "category_ids": [
      8
    ],
    "entities": [
      {
        "id": 4605219597,
        "language": "en",
        "region": "NO"
      },
      {
        "id": 4551071098,
        "language": "en",
        "region": "NO"
      },
      {
        "id": 4607625834,
        "language": "en",
        "region": "NO"
      },
      {
        "id": 4602012453,
        "language": "en",
        "region": "NO"
      },
      {
        "id": 4607848640,
        "language": "en",
        "region": "NO"
      },
      {
        "id": 4607204549,
        "language": "en",
        "region": "NO"
      }
    ],
    "normalized_keyword": "17.mai 2026",
    "captured_at": "2026-05-18T06:59:34.801701+00:00"
  },
  {
    "keyword": "christian ringnes",
    "region": "NO",
    "started_at_unix": 1779022800,
    "ended_at_unix": 1779031200,
    "search_volume": 200,
    "score": 900,
    "related_queries": [
      "christian ringnes"
    ],
    "category_ids": [
      10
    ],
    "entities": [
      {
        "id": 4598152700,
        "language": "en",
        "region": "NO"
      },
      {
        "id": 4588940818,
        "language": "en",
        "region": "NO"
      }
    ],
    "normalized_keyword": "christian ringnes",
    "captured_at": "2026-05-18T06:59:34.801701+00:00"
  },
  {
    "keyword": "hockey vm 2026",
    "region": "NO",
    "started_at_unix": 1779049200,
    "ended_at_unix": 1779054000,
    "search_volume": 100,
    "score": 300,
    "related_queries": [
      "hockey vm 2026"
    ],
    "category_ids": [
      17
    ],
    "entities": [
      {
        "id": 4598561411,
        "language": "sv",
        "region": "NO"
      },
      {
        "id": 4606144405,
        "language": "sv",
        "region": "NO"
      },
      {
        "id": 4566004597,
        "language": "sv",
        "region": "NO"
      },
      {
        "id": 4606333016,
        "language": "sv",
        "region": "NO"
      },
      {
        "id": 4604115375,
        "language": "sv",
        "region": "NO"
      },
      {
        "id": 4606694396,
        "language": "sv",
        "region": "NO"
      },
      {
        "id": 4608202023,
        "language": "sv",
        "region": "NO"
      },
      {
        "id": 4601637319,
        "language": "sv",
        "region": "NO"
      },
      {
        "id": 4606724433,
        "language": "sv",
        "region": "NO"
      }
    ],
    "normalized_keyword": "hockey vm 2026",
    "captured_at": "2026-05-18T06:59:34.801701+00:00"
  },
  {
    "keyword": "17. mai oslo",
    "region": "NO",
    "started_at_unix": 1779002400,
    "ended_at_unix": 1779014400,
    "search_volume": 200,
    "score": 800,
    "related_queries": [
      "17. mai oslo"
    ],
    "category_ids": [
      11
    ],
    "entities": [
      {
        "id": 4599697454,
        "language": "de",
        "region": "NO"
      },
      {
        "id": 4607307490,
        "language": "de",
        "region": "NO"
      },
      {
        "id": 4607084073,
        "language": "de",
        "region": "NO"
      },
      {
        "id": 4597099587,
        "language": "de",
        "region": "NO"
      },
      {
        "id": 4607577066,
        "language": "de",
        "region": "NO"
      },
      {
        "id": 4607539676,
        "language": "de",
        "region": "NO"
      },
      {
        "id": 4551071098,
        "language": "de",
        "region": "NO"
      }
    ],
    "normalized_keyword": "17. mai oslo",
    "captured_at": "2026-05-18T06:59:34.801701+00:00"
  },
  {
    "keyword": "jacob berglund",
    "region": "NO",
    "started_at_unix": 1779049800,
    "ended_at_unix": 1779053400,
    "search_volume": 100,
    "score": 1000,
    "related_queries": [
      "jacob berglund"
    ],
    "category_ids": [
      17
    ],
    "entities": [
      {
        "id": 4608288499,
        "language": "sv",
        "region": "NO"
      },
      {
        "id": 4598577854,
        "language": "sv",
        "region": "NO"
      }
    ],
    "normalized_keyword": "jacob berglund",
    "captured_at": "2026-05-18T06:59:34.801701+00:00"
  },
  {
    "keyword": "casemiro",
    "region": "NO",
    "started_at_unix": 1779023400,
    "ended_at_unix": 1779029400,
    "search_volume": 200,
    "score": 900,
    "related_queries": [
      "casemiro"
    ],
    "category_ids": [
      17
    ],
    "entities": [
      {
        "id": 4583261387,
        "language": "en",
        "region": "NO"
      },
      {
        "id": 4608271103,
        "language": "en",
        "region": "NO"
      },
      {
        "id": 4599735512,
        "language": "en",
        "region": "NO"
      },
      {
        "id": 4607848574,
        "language": "en",
        "region": "NO"
      },
      {
        "id": 4596657609,
        "language": "en",
        "region": "NO"
      }
    ],
    "normalized_keyword": "casemiro",
    "captured_at": "2026-05-18T06:59:34.801701+00:00"
  },
  {
    "keyword": "alexander sørloth",
    "region": "NO",
    "started_at_unix": 1779045600,
    "ended_at_unix": 1779048600,
    "search_volume": 200,
    "score": 1000,
    "related_queries": [
      "alexander sørloth"
    ],
    "category_ids": [
      17
    ],
    "entities": [
      {
        "id": 4603348691,
        "language": "en",
        "region": "NO"
      },
      {
        "id": 4607402552,
        "language": "en",
        "region": "NO"
      }
    ],
    "normalized_keyword": "alexander sørloth",
    "captured_at": "2026-05-18T06:59:34.801701+00:00"
  },
  {
    "keyword": "gratulerer med dagen 17 mai",
    "region": "NO",
    "started_at_unix": 1779001800,
    "ended_at_unix": 1779014400,
    "search_volume": 200,
    "score": 800,
    "related_queries": [
      "gratulerer med dagen 17 mai"
    ],
    "category_ids": [
      8
    ],
    "entities": [
      {
        "id": 4608256185,
        "language": "no",
        "region": "NO"
      },
      {
        "id": 4608288448,
        "language": "no",
        "region": "NO"
      },
      {
        "id": 4597099587,
        "language": "no",
        "region": "NO"
      },
      {
        "id": 4607204549,
        "language": "no",
        "region": "NO"
      },
      {
        "id": 4608216582,
        "language": "no",
        "region": "NO"
      },
      {
        "id": 4596989911,
        "language": "no",
        "region": "NO"
      }
    ],
    "normalized_keyword": "gratulerer med dagen 17 mai",
    "captured_at": "2026-05-18T06:59:34.801701+00:00"
  },
  {
    "keyword": "borgertog trondheim",
    "region": "NO",
    "started_at_unix": 1779016200,
    "ended_at_unix": 1779021600,
    "search_volume": 200,
    "score": 1000,
    "related_queries": [
      "borgertog trondheim"
    ],
    "category_ids": [
      11
    ],
    "entities": [
      {
        "id": 4607808648,
        "language": "en",
        "region": "NO"
      },
      {
        "id": 4607672375,
        "language": "en",
        "region": "NO"
      }
    ],
    "normalized_keyword": "borgertog trondheim",
    "captured_at": "2026-05-18T06:59:34.801701+00:00"
  },
  {
    "keyword": "markus neby",
    "region": "NO",
    "started_at_unix": 1779019200,
    "ended_at_unix": 1779023400,
    "search_volume": 200,
    "score": 1000,
    "related_queries": [
      "markus neby"
    ],
    "category_ids": [
      11
    ],
    "entities": [
      {
        "id": 4601520157,
        "language": "en",
        "region": "NO"
      }
    ],
    "normalized_keyword": "markus neby",
    "captured_at": "2026-05-18T06:59:34.801701+00:00"
  },
  {
    "keyword": "lechia – legia warszawa",
    "region": "NO",
    "started_at_unix": 1779033600,
    "ended_at_unix": 1779037800,
    "search_volume": 100,
    "score": 1000,
    "related_queries": [
      "lechia – legia warszawa"
    ],
    "category_ids": [
      17
    ],
    "entities": [
      {
        "id": 4579542295,
        "language": "pl",
        "region": "NO"
      }
    ],
    "normalized_keyword": "lechia – legia warszawa",
    "captured_at": "2026-05-18T06:59:34.801701+00:00"
  },
  {
    "keyword": "ørje",
    "region": "NO",
    "started_at_unix": 1779007800,
    "ended_at_unix": 1779012000,
    "search_volume": 200,
    "score": 1000,
    "related_queries": [
      "ørje"
    ],
    "category_ids": [
      17,
      4
    ],
    "entities": [
      {
        "id": 4606257613,
        "language": "en",
        "region": "NO"
      },
      {
        "id": 4606530263,
        "language": "en",
        "region": "NO"
      }
    ],
    "normalized_keyword": "ørje",
    "captured_at": "2026-05-18T06:59:34.801701+00:00"
  },
  {
    "keyword": "mcdonalds",
    "region": "NO",
    "started_at_unix": 1779058800,
    "ended_at_unix": 1779067800,
    "search_volume": 100,
    "score": 300,
    "related_queries": [
      "mcdonalds"
    ],
    "category_ids": [
      10,
      5
    ],
    "entities": [
      {
        "id": 4603184308,
        "language": "en",
        "region": "NO"
      }
    ],
    "normalized_keyword": "mcdonalds",
    "captured_at": "2026-05-18T06:59:34.801701+00:00"
  },
  {
    "keyword": "russetid 2026",
    "region": "NO",
    "started_at_unix": 1779016200,
    "ended_at_unix": 1779021000,
    "search_volume": 100,
    "score": 500,
    "related_queries": [
      "russetid 2026"
    ],
    "category_ids": [
      8
    ],
    "entities": [
      {
        "id": 4605782485,
        "language": "en",
        "region": "NO"
      },
      {
        "id": 4589814023,
        "language": "en",
        "region": "NO"
      }
    ],
    "normalized_keyword": "russetid 2026",
    "captured_at": "2026-05-18T06:59:34.801701+00:00"
  },
  {
    "keyword": "manu",
    "region": "NO",
    "started_at_unix": 1779024000,
    "ended_at_unix": 1779027600,
    "search_volume": 100,
    "score": 1000,
    "related_queries": [
      "manu"
    ],
    "category_ids": [
      17
    ],
    "entities": [
      {
        "id": 4607453782,
        "language": "en",
        "region": "NO"
      }
    ],
    "normalized_keyword": "manu",
    "captured_at": "2026-05-18T06:59:34.801701+00:00"
  },
  {
    "keyword": "sverre magnus av norge",
    "region": "NO",
    "started_at_unix": 1779016200,
    "ended_at_unix": 1779017400,
    "search_volume": 500,
    "score": 1000,
    "related_queries": [
      "sverre magnus av norge"
    ],
    "category_ids": [
      10
    ],
    "entities": [
      {
        "id": 4608172007,
        "language": "no",
        "region": "NO"
      },
      {
        "id": 4587133547,
        "language": "no",
        "region": "NO"
      }
    ],
    "normalized_keyword": "sverre magnus av norge",
    "captured_at": "2026-05-18T06:59:34.801701+00:00"
  },
  {
    "keyword": "vm 2026",
    "region": "NO",
    "started_at_unix": 1779020400,
    "ended_at_unix": 1779023400,
    "search_volume": 100,
    "score": 400,
    "related_queries": [
      "vm 2026"
    ],
    "category_ids": [
      17
    ],
    "entities": [
      {
        "id": 4604421012,
        "language": "en",
        "region": "NO"
      },
      {
        "id": 4607963732,
        "language": "en",
        "region": "NO"
      },
      {
        "id": 4593067337,
        "language": "en",
        "region": "NO"
      },
      {
        "id": 4519250111,
        "language": "en",
        "region": "NO"
      }
    ],
    "normalized_keyword": "vm 2026",
    "captured_at": "2026-05-18T06:59:34.801701+00:00"
  },
  {
    "keyword": "serie a",
    "region": "NO",
    "started_at_unix": 1779020400,
    "ended_at_unix": 1779023400,
    "search_volume": 100,
    "score": 600,
    "related_queries": [
      "serie a"
    ],
    "category_ids": [
      17
    ],
    "entities": [
      {
        "id": 4598911671,
        "language": "it",
        "region": "NO"
      },
      {
        "id": 4598897942,
        "language": "it",
        "region": "NO"
      },
      {
        "id": 4607667500,
        "language": "it",
        "region": "NO"
      },
      {
        "id": 4600004607,
        "language": "it",
        "region": "NO"
      },
      {
        "id": 4598564638,
        "language": "it",
        "region": "NO"
      },
      {
        "id": 4600443358,
        "language": "it",
        "region": "NO"
      },
      {
        "id": 4601492558,
        "language": "it",
        "region": "NO"
      },
      {
        "id": 4585499128,
        "language": "it",
        "region": "NO"
      },
      {
        "id": 4593524319,
        "language": "it",
        "region": "NO"
      },
      {
        "id": 4590471676,
        "language": "it",
        "region": "NO"
      },
      {
        "id": 4582299641,
        "language": "it",
        "region": "NO"
      }
    ],
    "normalized_keyword": "serie a",
    "captured_at": "2026-05-18T06:59:34.801701+00:00"
  },
  {
    "keyword": "itromsø",
    "region": "NO",
    "started_at_unix": 1779033600,
    "ended_at_unix": 1779036000,
    "search_volume": 100,
    "score": 200,
    "related_queries": [
      "itromsø"
    ],
    "category_ids": [
      11
    ],
    "entities": [
      {
        "id": 4608828923,
        "language": "en",
        "region": "NO"
      },
      {
        "id": 4602318861,
        "language": "en",
        "region": "NO"
      },
      {
        "id": 4608883221,
        "language": "en",
        "region": "NO"
      },
      {
        "id": 4607307522,
        "language": "en",
        "region": "NO"
      },
      {
        "id": 4589868190,
        "language": "en",
        "region": "NO"
      },
      {
        "id": 4593799976,
        "language": "en",
        "region": "NO"
      }
    ],
    "normalized_keyword": "itromsø",
    "captured_at": "2026-05-18T06:59:34.801701+00:00"
  },
  {
    "keyword": "fotball vm 2026",
    "region": "NO",
    "started_at_unix": 1779021000,
    "ended_at_unix": 1779023400,
    "search_volume": 100,
    "score": 400,
    "related_queries": [
      "fotball vm 2026"
    ],
    "category_ids": [
      17
    ],
    "entities": [
      {
        "id": 4593067337,
        "language": "no",
        "region": "NO"
      },
      {
        "id": 4572509112,
        "language": "no",
        "region": "NO"
      },
      {
        "id": 4607963732,
        "language": "no",
        "region": "NO"
      },
      {
        "id": 4604421012,
        "language": "no",
        "region": "NO"
      }
    ],
    "normalized_keyword": "fotball vm 2026",
    "captured_at": "2026-05-18T06:59:34.801701+00:00"
  },
  {
    "keyword": "manchester united fc",
    "region": "NO",
    "started_at_unix": 1779036000,
    "ended_at_unix": 1779037200,
    "search_volume": 100,
    "score": 400,
    "related_queries": [
      "manchester united fc"
    ],
    "category_ids": [
      17
    ],
    "entities": [
      {
        "id": 4600866776,
        "language": "en",
        "region": "NO"
      },
      {
        "id": 4599735512,
        "language": "en",
        "region": "NO"
      },
      {
        "id": 4581671770,
        "language": "en",
        "region": "NO"
      },
      {
        "id": 4607135492,
        "language": "en",
        "region": "NO"
      },
      {
        "id": 4607282573,
        "language": "en",
        "region": "NO"
      },
      {
        "id": 4603001652,
        "language": "en",
        "region": "NO"
      },
      {
        "id": 4583807469,
        "language": "en",
        "region": "NO"
      },
      {
        "id": 4599075918,
        "language": "en",
        "region": "NO"
      },
      {
        "id": 4574428089,
        "language": "en",
        "region": "NO"
      }
    ],
    "normalized_keyword": "manchester united fc",
    "captured_at": "2026-05-18T06:59:34.801701+00:00"
  }
]