[
  {
    "keyword": "uføretrygd",
    "region": "NO",
    "started_at_unix": 1778584800,
    "ended_at_unix": null,
    "search_volume": 10000,
    "score": 1000,
    "related_queries": [
      "uføretrygd"
    ],
    "category_ids": [
      10,
      3
    ],
    "entities": [
      {
        "id": 4596948734,
        "language": "en",
        "region": "NO"
      },
      {
        "id": 4586382356,
        "language": "en",
        "region": "NO"
      }
    ],
    "normalized_keyword": "uføretrygd",
    "captured_at": "2026-05-13T06:23:03.872572+00:00"
  },
  {
    "keyword": "kristoffer ingebrigtsen",
    "region": "NO",
    "started_at_unix": 1778578200,
    "ended_at_unix": null,
    "search_volume": 5000,
    "score": 1000,
    "related_queries": [
      "kristoffer ingebrigtsen"
    ],
    "category_ids": [
      17
    ],
    "entities": [
      {
        "id": 4596730050,
        "language": "en",
        "region": "NO"
      }
    ],
    "normalized_keyword": "kristoffer ingebrigtsen",
    "captured_at": "2026-05-13T06:23:03.872572+00:00"
  },
  {
    "keyword": "snø",
    "region": "NO",
    "started_at_unix": 1778590200,
    "ended_at_unix": null,
    "search_volume": 5000,
    "score": 1000,
    "related_queries": [
      "snø"
    ],
    "category_ids": [
      11
    ],
    "entities": [
      {
        "id": 4578319672,
        "language": "en",
        "region": "NO"
      },
      {
        "id": 4551071098,
        "language": "en",
        "region": "NO"
      },
      {
        "id": 4596989902,
        "language": "en",
        "region": "NO"
      },
      {
        "id": 4597489440,
        "language": "en",
        "region": "NO"
      }
    ],
    "normalized_keyword": "snø",
    "captured_at": "2026-05-13T06:23:03.872572+00:00"
  },
  {
    "keyword": "lindsey vonn",
    "region": "NO",
    "started_at_unix": 1778594400,
    "ended_at_unix": null,
    "search_volume": 2000,
    "score": 1000,
    "related_queries": [
      "lindsey vonn"
    ],
    "category_ids": [
      17
    ],
    "entities": [
      {
        "id": 4590365903,
        "language": "en",
        "region": "NO"
      },
      {
        "id": 4598398440,
        "language": "en",
        "region": "NO"
      },
      {
        "id": 4596569335,
        "language": "en",
        "region": "NO"
      },
      {
        "id": 4569370171,
        "language": "en",
        "region": "NO"
      },
      {
        "id": 4591203584,
        "language": "en",
        "region": "NO"
      }
    ],
    "normalized_keyword": "lindsey vonn",
    "captured_at": "2026-05-13T06:23:03.872572+00:00"
  },
  {
    "keyword": "arsenal fc",
    "region": "NO",
    "started_at_unix": 1778601000,
    "ended_at_unix": null,
    "search_volume": 5000,
    "score": 1000,
    "related_queries": [
      "arsenal fc"
    ],
    "category_ids": [
      17
    ],
    "entities": [
      {
        "id": 4597669724,
        "language": "en",
        "region": "NO"
      },
      {
        "id": 4598832688,
        "language": "en",
        "region": "NO"
      },
      {
        "id": 4583637394,
        "language": "en",
        "region": "NO"
      },
      {
        "id": 4595015959,
        "language": "en",
        "region": "NO"
      },
      {
        "id": 4597699326,
        "language": "en",
        "region": "NO"
      },
      {
        "id": 4585773129,
        "language": "en",
        "region": "NO"
      },
      {
        "id": 4589377398,
        "language": "en",
        "region": "NO"
      },
      {
        "id": 4593388210,
        "language": "en",
        "region": "NO"
      }
    ],
    "normalized_keyword": "arsenal fc",
    "captured_at": "2026-05-13T06:23:03.872572+00:00"
  },
  {
    "keyword": "osasuna mot atlético madrid",
    "region": "NO",
    "started_at_unix": 1778611800,
    "ended_at_unix": null,
    "search_volume": 2000,
    "score": 1000,
    "related_queries": [
      "osasuna mot atlético madrid"
    ],
    "category_ids": [
      17
    ],
    "entities": [
      {
        "id": 4590674295,
        "language": "es",
        "region": "NO"
      },
      {
        "id": 4598106946,
        "language": "es",
        "region": "NO"
      },
      {
        "id": 4590447788,
        "language": "es",
        "region": "NO"
      }
    ],
    "normalized_keyword": "osasuna mot atletico madrid",
    "captured_at": "2026-05-13T06:23:03.872572+00:00"
  },
  {
    "keyword": "europa",
    "region": "NO",
    "started_at_unix": 1778616000,
    "ended_at_unix": null,
    "search_volume": 1000,
    "score": 1000,
    "related_queries": [
      "europa"
    ],
    "category_ids": [
      10
    ],
    "entities": [
      {
        "id": 4580280302,
        "language": "es",
        "region": "NO"
      },
      {
        "id": 4594956134,
        "language": "es",
        "region": "NO"
      },
      {
        "id": 4589492827,
        "language": "es",
        "region": "NO"
      },
      {
        "id": 4591558422,
        "language": "es",
        "region": "NO"
      },
      {
        "id": 4594210172,
        "language": "es",
        "region": "NO"
      },
      {
        "id": 4598759499,
        "language": "es",
        "region": "NO"
      },
      {
        "id": 4597465557,
        "language": "es",
        "region": "NO"
      },
      {
        "id": 4598680852,
        "language": "es",
        "region": "NO"
      },
      {
        "id": 4598653632,
        "language": "es",
        "region": "NO"
      }
    ],
    "normalized_keyword": "europa",
    "captured_at": "2026-05-13T06:23:03.872572+00:00"
  },
  {
    "keyword": "johannes høsflot klæbo",
    "region": "NO",
    "started_at_unix": 1778620200,
    "ended_at_unix": null,
    "search_volume": 1000,
    "score": 700,
    "related_queries": [
      "johannes høsflot klæbo"
    ],
    "category_ids": [
      17
    ],
    "entities": [
      {
        "id": 4597963908,
        "language": "en",
        "region": "NO"
      },
      {
        "id": 4596362850,
        "language": "en",
        "region": "NO"
      },
      {
        "id": 4598661420,
        "language": "en",
        "region": "NO"
      },
      {
        "id": 4594524738,
        "language": "en",
        "region": "NO"
      },
      {
        "id": 4567507080,
        "language": "en",
        "region": "NO"
      },
      {
        "id": 4593123050,
        "language": "en",
        "region": "NO"
      }
    ],
    "normalized_keyword": "johannes høsflot klæbo",
    "captured_at": "2026-05-13T06:23:03.872572+00:00"
  },
  {
    "keyword": "revidert nasjonalbudsjett",
    "region": "NO",
    "started_at_unix": 1778567400,
    "ended_at_unix": null,
    "search_volume": 2000,
    "score": 900,
    "related_queries": [
      "revidert nasjonalbudsjett",
      "regjering",
      "revidert nasjonalbudsjett 2026"
    ],
    "category_ids": [
      11
    ],
    "entities": [
      {
        "id": 4564012515,
        "language": "en",
        "region": "NO"
      },
      {
        "id": 4590356784,
        "language": "en",
        "region": "NO"
      },
      {
        "id": 4586164726,
        "language": "en",
        "region": "NO"
      },
      {
        "id": 4596689168,
        "language": "en",
        "region": "NO"
      },
      {
        "id": 4597999369,
        "language": "en",
        "region": "NO"
      },
      {
        "id": 4578018932,
        "language": "en",
        "region": "NO"
      },
      {
        "id": 4596904381,
        "language": "en",
        "region": "NO"
      },
      {
        "id": 4564012515,
        "language": "no",
        "region": "NO"
      },
      {
        "id": 4579915492,
        "language": "no",
        "region": "NO"
      },
      {
        "id": 4561685921,
        "language": "no",
        "region": "NO"
      },
      {
        "id": 4590356784,
        "language": "no",
        "region": "NO"
      },
      {
        "id": 4597176520,
        "language": "no",
        "region": "NO"
      },
      {
        "id": 4596689168,
        "language": "no",
        "region": "NO"
      },
      {
        "id": 4591233786,
        "language": "no",
        "region": "NO"
      },
      {
        "id": 4598796114,
        "language": "no",
        "region": "NO"
      },
      {
        "id": 4578018932,
        "language": "no",
        "region": "NO"
      },
      {
        "id": 4597690515,
        "language": "no",
        "region": "NO"
      }
    ],
    "normalized_keyword": "revidert nasjonalbudsjett",
    "captured_at": "2026-05-13T06:23:03.872572+00:00"
  },
  {
    "keyword": "brandon clarke",
    "region": "NO",
    "started_at_unix": 1778611200,
    "ended_at_unix": null,
    "search_volume": 2000,
    "score": 1000,
    "related_queries": [
      "brandon clarke",
      "brandon clark"
    ],
    "category_ids": [
      17
    ],
    "entities": [
      {
        "id": 4597833612,
        "language": "en",
        "region": "NO"
      },
      {
        "id": 4597856029,
        "language": "en",
        "region": "NO"
      }
    ],
    "normalized_keyword": "brandon clarke",
    "captured_at": "2026-05-13T06:23:03.872572+00:00"
  },
  {
    "keyword": "sofie marhaug",
    "region": "NO",
    "started_at_unix": 1778643000,
    "ended_at_unix": null,
    "search_volume": 200,
    "score": 900,
    "related_queries": [
      "sofie marhaug"
    ],
    "category_ids": [
      11
    ],
    "entities": [
      {
        "id": 4597856007,
        "language": "en",
        "region": "NO"
      }
    ],
    "normalized_keyword": "sofie marhaug",
    "captured_at": "2026-05-13T06:23:03.872572+00:00"
  },
  {
    "keyword": "al nassr",
    "region": "NO",
    "started_at_unix": 1778611800,
    "ended_at_unix": null,
    "search_volume": 1000,
    "score": 800,
    "related_queries": [
      "al nassr"
    ],
    "category_ids": [
      17
    ],
    "entities": [
      {
        "id": 4573075796,
        "language": "en",
        "region": "NO"
      }
    ],
    "normalized_keyword": "al nassr",
    "captured_at": "2026-05-13T06:23:03.872572+00:00"
  },
  {
    "keyword": "saudi-arabia",
    "region": "NO",
    "started_at_unix": 1778650200,
    "ended_at_unix": null,
    "search_volume": 200,
    "score": 1000,
    "related_queries": [
      "saudi-arabia"
    ],
    "category_ids": [
      11
    ],
    "entities": [
      {
        "id": 4597845395,
        "language": "en",
        "region": "NO"
      },
      {
        "id": 4598187792,
        "language": "en",
        "region": "NO"
      },
      {
        "id": 4598237553,
        "language": "en",
        "region": "NO"
      },
      {
        "id": 4586012581,
        "language": "en",
        "region": "NO"
      },
      {
        "id": 4595231072,
        "language": "en",
        "region": "NO"
      },
      {
        "id": 4592955910,
        "language": "en",
        "region": "NO"
      },
      {
        "id": 4593713939,
        "language": "en",
        "region": "NO"
      },
      {
        "id": 4573075796,
        "language": "en",
        "region": "NO"
      },
      {
        "id": 4576183874,
        "language": "en",
        "region": "NO"
      }
    ],
    "normalized_keyword": "saudi-arabia",
    "captured_at": "2026-05-13T06:23:03.872572+00:00"
  },
  {
    "keyword": "2026",
    "region": "NO",
    "started_at_unix": 1778581200,
    "ended_at_unix": 1778649600,
    "search_volume": 5000,
    "score": 1000,
    "related_queries": [
      "2026"
    ],
    "category_ids": [
      14
    ],
    "entities": [
      {
        "id": 4588456967,
        "language": "en",
        "region": "US"
      },
      {
        "id": 4572268832,
        "language": "en",
        "region": "US"
      },
      {
        "id": 4598837404,
        "language": "en",
        "region": "US"
      },
      {
        "id": 4560620327,
        "language": "en",
        "region": "US"
      },
      {
        "id": 4598776187,
        "language": "en",
        "region": "US"
      },
      {
        "id": 4561164350,
        "language": "en",
        "region": "US"
      },
      {
        "id": 4580946183,
        "language": "en",
        "region": "US"
      },
      {
        "id": 4598007206,
        "language": "en",
        "region": "US"
      },
      {
        "id": 4578969070,
        "language": "en",
        "region": "US"
      }
    ],
    "normalized_keyword": "2026",
    "captured_at": "2026-05-13T06:23:03.872572+00:00"
  },
  {
    "keyword": "gta 6",
    "region": "NO",
    "started_at_unix": 1778652000,
    "ended_at_unix": null,
    "search_volume": 200,
    "score": 400,
    "related_queries": [
      "gta 6",
      "grand theft auto vi"
    ],
    "category_ids": [
      6
    ],
    "entities": [
      {
        "id": 4570074450,
        "language": "en",
        "region": "NO"
      },
      {
        "id": 4585113659,
        "language": "en",
        "region": "NO"
      },
      {
        "id": 4547481992,
        "language": "en",
        "region": "NO"
      },
      {
        "id": 4598593696,
        "language": "en",
        "region": "NO"
      }
    ],
    "normalized_keyword": "gta 6",
    "captured_at": "2026-05-13T06:23:03.872572+00:00"
  },
  {
    "keyword": "enebakk",
    "region": "NO",
    "started_at_unix": 1778605800,
    "ended_at_unix": 1778652000,
    "search_volume": 2000,
    "score": 1000,
    "related_queries": [
      "enebakk",
      "enebakk avis",
      "ytre enebakk"
    ],
    "category_ids": [
      11
    ],
    "entities": [
      {
        "id": 4597690439,
        "language": "en",
        "region": "NO"
      },
      {
        "id": 4595907852,
        "language": "en",
        "region": "NO"
      },
      {
        "id": 4595907791,
        "language": "en",
        "region": "NO"
      },
      {
        "id": 4598185808,
        "language": "en",
        "region": "NO"
      },
      {
        "id": 4595649824,
        "language": "en",
        "region": "NO"
      },
      {
        "id": 4592450293,
        "language": "en",
        "region": "NO"
      }
    ],
    "normalized_keyword": "enebakk",
    "captured_at": "2026-05-13T06:23:03.872572+00:00"
  },
  {
    "keyword": "eurovision",
    "region": "NO",
    "started_at_unix": 1778605200,
    "ended_at_unix": 1778652600,
    "search_volume": 2000,
    "score": 500,
    "related_queries": [
      "eurovision",
      "semifinale",
      "semifinale 1 eurovision 2026",
      "finland eurovision 2026",
      "melodi grand prix 2026",
      "nrk eurovision",
      "eurovision song contest"
    ],
    "category_ids": [
      4
    ],
    "entities": [
      {
        "id": 4597134890,
        "language": "en",
        "region": "NO"
      },
      {
        "id": 4587510663,
        "language": "en",
        "region": "NO"
      },
      {
        "id": 4584345732,
        "language": "en",
        "region": "NO"
      },
      {
        "id": 4595247375,
        "language": "en",
        "region": "NO"
      },
      {
        "id": 4557661894,
        "language": "en",
        "region": "NO"
      },
      {
        "id": 4597134890,
        "language": "it",
        "region": "NO"
      },
      {
        "id": 4580354292,
        "language": "it",
        "region": "NO"
      },
      {
        "id": 4579728030,
        "language": "it",
        "region": "NO"
      },
      {
        "id": 4545871085,
        "language": "it",
        "region": "NO"
      },
      {
        "id": 4558293745,
        "language": "it",
        "region": "NO"
      },
      {
        "id": 4598170133,
        "language": "it",
        "region": "NO"
      },
      {
        "id": 4595227740,
        "language": "it",
        "region": "NO"
      },
      {
        "id": 4586734259,
        "language": "it",
        "region": "NO"
      },
      {
        "id": 4591111059,
        "language": "it",
        "region": "NO"
      },
      {
        "id": 4597034973,
        "language": "it",
        "region": "NO"
      },
      {
        "id": 4596226410,
        "language": "it",
        "region": "NO"
      },
      {
        "id": 4597728742,
        "language": "it",
        "region": "NO"
      },
      {
        "id": 4395474004,
        "language": "en",
        "region": "NO"
      },
      {
        "id": 4588504624,
        "language": "en",
        "region": "NO"
      },
      {
        "id": 4597440378,
        "language": "en",
        "region": "NO"
      }
    ],
    "normalized_keyword": "eurovision",
    "captured_at": "2026-05-13T06:23:03.872572+00:00"
  },
  {
    "keyword": "johannes moesgaard",
    "region": "NO",
    "started_at_unix": 1778605200,
    "ended_at_unix": null,
    "search_volume": 200,
    "score": 500,
    "related_queries": [
      "johannes moesgaard"
    ],
    "category_ids": [
      17
    ],
    "entities": [
      {
        "id": 4584170887,
        "language": "en",
        "region": "NO"
      },
      {
        "id": 4593391723,
        "language": "en",
        "region": "NO"
      }
    ],
    "normalized_keyword": "johannes moesgaard",
    "captured_at": "2026-05-13T06:23:03.872572+00:00"
  },
  {
    "keyword": "kreml",
    "region": "NO",
    "started_at_unix": 1778589600,
    "ended_at_unix": 1778626800,
    "search_volume": 2000,
    "score": 1000,
    "related_queries": [
      "kreml"
    ],
    "category_ids": [
      10
    ],
    "entities": [
      {
        "id": 4569924101,
        "language": "de",
        "region": "NO"
      },
      {
        "id": 4577665910,
        "language": "de",
        "region": "NO"
      },
      {
        "id": 4590942452,
        "language": "de",
        "region": "NO"
      },
      {
        "id": 4598617577,
        "language": "de",
        "region": "NO"
      },
      {
        "id": 4592687544,
        "language": "de",
        "region": "NO"
      },
      {
        "id": 4586945855,
        "language": "de",
        "region": "NO"
      },
      {
        "id": 4573335875,
        "language": "de",
        "region": "NO"
      },
      {
        "id": 4552691113,
        "language": "de",
        "region": "NO"
      },
      {
        "id": 4534346845,
        "language": "de",
        "region": "NO"
      }
    ],
    "normalized_keyword": "kreml",
    "captured_at": "2026-05-13T06:23:03.872572+00:00"
  },
  {
    "keyword": "boy george",
    "region": "NO",
    "started_at_unix": 1778617200,
    "ended_at_unix": 1778626800,
    "search_volume": 2000,
    "score": 1000,
    "related_queries": [
      "boy george",
      "san marino"
    ],
    "category_ids": [
      4
    ],
    "entities": [
      {
        "id": 4589926623,
        "language": "en",
        "region": "US"
      },
      {
        "id": 4597508139,
        "language": "en",
        "region": "US"
      },
      {
        "id": 4586509688,
        "language": "en",
        "region": "US"
      },
      {
        "id": 4597093670,
        "language": "en",
        "region": "US"
      },
      {
        "id": 4578503986,
        "language": "en",
        "region": "US"
      },
      {
        "id": 4587251481,
        "language": "en",
        "region": "US"
      }
    ],
    "normalized_keyword": "boy george",
    "captured_at": "2026-05-13T06:23:03.872572+00:00"
  },
  {
    "keyword": "rein alexander",
    "region": "NO",
    "started_at_unix": 1778572800,
    "ended_at_unix": 1778618400,
    "search_volume": 2000,
    "score": 1000,
    "related_queries": [
      "rein alexander"
    ],
    "category_ids": [
      11
    ],
    "entities": [
      {
        "id": 4596312048,
        "language": "en",
        "region": "NO"
      }
    ],
    "normalized_keyword": "rein alexander",
    "captured_at": "2026-05-13T06:23:03.872572+00:00"
  },
  {
    "keyword": "jonas lovv",
    "region": "NO",
    "started_at_unix": 1778609400,
    "ended_at_unix": 1778652000,
    "search_volume": 500,
    "score": 300,
    "related_queries": [
      "jonas lovv"
    ],
    "category_ids": [
      4
    ],
    "entities": [
      {
        "id": 4585153758,
        "language": "en",
        "region": "US"
      }
    ],
    "normalized_keyword": "jonas lovv",
    "captured_at": "2026-05-13T06:23:03.872572+00:00"
  },
  {
    "keyword": "jon almaas",
    "region": "NO",
    "started_at_unix": 1778610600,
    "ended_at_unix": 1778649600,
    "search_volume": 1000,
    "score": 1000,
    "related_queries": [
      "jon almaas"
    ],
    "category_ids": [
      13,
      8,
      4
    ],
    "entities": [
      {
        "id": 4597690502,
        "language": "en",
        "region": "NO"
      },
      {
        "id": 4593476482,
        "language": "en",
        "region": "NO"
      },
      {
        "id": 4589310067,
        "language": "en",
        "region": "NO"
      }
    ],
    "normalized_keyword": "jon almaas",
    "captured_at": "2026-05-13T06:23:03.872572+00:00"
  },
  {
    "keyword": "john christian elden",
    "region": "NO",
    "started_at_unix": 1778583000,
    "ended_at_unix": 1778607600,
    "search_volume": 2000,
    "score": 1000,
    "related_queries": [
      "john christian elden"
    ],
    "category_ids": [
      11
    ],
    "entities": [
      {
        "id": 4596904304,
        "language": "en",
        "region": "NO"
      },
      {
        "id": 4570685979,
        "language": "en",
        "region": "NO"
      }
    ],
    "normalized_keyword": "john christian elden",
    "captured_at": "2026-05-13T06:23:03.872572+00:00"
  },
  {
    "keyword": "eiendomsskatt",
    "region": "NO",
    "started_at_unix": 1778600400,
    "ended_at_unix": 1778647200,
    "search_volume": 1000,
    "score": 1000,
    "related_queries": [
      "eiendomsskatt"
    ],
    "category_ids": [
      11
    ],
    "entities": [
      {
        "id": 4598047685,
        "language": "en",
        "region": "NO"
      },
      {
        "id": 4597931048,
        "language": "en",
        "region": "NO"
      }
    ],
    "normalized_keyword": "eiendomsskatt",
    "captured_at": "2026-05-13T06:23:03.872572+00:00"
  },
  {
    "keyword": "spotify down",
    "region": "NO",
    "started_at_unix": 1778605800,
    "ended_at_unix": 1778617200,
    "search_volume": 2000,
    "score": 1000,
    "related_queries": [
      "spotify down",
      "is spotify down",
      "spotify problems",
      "downdetector"
    ],
    "category_ids": [
      18
    ],
    "entities": [
      {
        "id": 4594321532,
        "language": "en",
        "region": "NO"
      },
      {
        "id": 4594321532,
        "language": "en",
        "region": "US"
      },
      {
        "id": 4595603195,
        "language": "en",
        "region": "US"
      },
      {
        "id": 4596436842,
        "language": "en",
        "region": "US"
      }
    ],
    "normalized_keyword": "spotify down",
    "captured_at": "2026-05-13T06:23:03.872572+00:00"
  },
  {
    "keyword": "meteorolog",
    "region": "NO",
    "started_at_unix": 1778595000,
    "ended_at_unix": 1778605200,
    "search_volume": 2000,
    "score": 1000,
    "related_queries": [
      "meteorolog"
    ],
    "category_ids": [
      11
    ],
    "entities": [
      {
        "id": 4551071098,
        "language": "sv",
        "region": "NO"
      }
    ],
    "normalized_keyword": "meteorolog",
    "captured_at": "2026-05-13T06:23:03.872572+00:00"
  },
  {
    "keyword": "17. mai",
    "region": "NO",
    "started_at_unix": 1778593800,
    "ended_at_unix": 1778614200,
    "search_volume": 1000,
    "score": 700,
    "related_queries": [
      "17. mai"
    ],
    "category_ids": [
      11
    ],
    "entities": [
      {
        "id": 4598386798,
        "language": "de",
        "region": "NO"
      },
      {
        "id": 4587133547,
        "language": "de",
        "region": "NO"
      },
      {
        "id": 4586826649,
        "language": "de",
        "region": "NO"
      },
      {
        "id": 4551071098,
        "language": "de",
        "region": "NO"
      },
      {
        "id": 4597690479,
        "language": "de",
        "region": "NO"
      },
      {
        "id": 4597963911,
        "language": "de",
        "region": "NO"
      }
    ],
    "normalized_keyword": "17. mai",
    "captured_at": "2026-05-13T06:23:03.872572+00:00"
  },
  {
    "keyword": "heidi weng",
    "region": "NO",
    "started_at_unix": 1778601000,
    "ended_at_unix": 1778618400,
    "search_volume": 500,
    "score": 1000,
    "related_queries": [
      "heidi weng"
    ],
    "category_ids": [
      17,
      4
    ],
    "entities": [
      {
        "id": 4597440334,
        "language": "en",
        "region": "NO"
      }
    ],
    "normalized_keyword": "heidi weng",
    "captured_at": "2026-05-13T06:23:03.872572+00:00"
  },
  {
    "keyword": "71 grader nord 2026",
    "region": "NO",
    "started_at_unix": 1778568000,
    "ended_at_unix": 1778604000,
    "search_volume": 1000,
    "score": 900,
    "related_queries": [
      "71 grader nord 2026",
      "71 nord - norges tøffeste kjendis",
      "71° nord - norges tøffeste kjendis"
    ],
    "category_ids": [
      4
    ],
    "entities": [
      {
        "id": 4585011991,
        "language": "no",
        "region": "NO"
      },
      {
        "id": 4585011991,
        "language": "en",
        "region": "NO"
      }
    ],
    "normalized_keyword": "71 grader nord 2026",
    "captured_at": "2026-05-13T06:23:03.872572+00:00"
  },
  {
    "keyword": "victoria swarovski",
    "region": "NO",
    "started_at_unix": 1778614800,
    "ended_at_unix": 1778624400,
    "search_volume": 500,
    "score": 1000,
    "related_queries": [
      "victoria swarovski"
    ],
    "category_ids": [
      4
    ],
    "entities": [
      {
        "id": 4593168432,
        "language": "de",
        "region": "NO"
      },
      {
        "id": 4598186151,
        "language": "de",
        "region": "NO"
      },
      {
        "id": 4587514239,
        "language": "de",
        "region": "NO"
      }
    ],
    "normalized_keyword": "victoria swarovski",
    "captured_at": "2026-05-13T06:23:03.872572+00:00"
  },
  {
    "keyword": "ansel elgort",
    "region": "NO",
    "started_at_unix": 1778617800,
    "ended_at_unix": 1778650800,
    "search_volume": 200,
    "score": 700,
    "related_queries": [
      "ansel elgort"
    ],
    "category_ids": [
      4
    ],
    "entities": [
      {
        "id": 4595788960,
        "language": "en",
        "region": "NO"
      }
    ],
    "normalized_keyword": "ansel elgort",
    "captured_at": "2026-05-13T06:23:03.872572+00:00"
  },
  {
    "keyword": "eurovision 2026 odds",
    "region": "NO",
    "started_at_unix": 1778614800,
    "ended_at_unix": 1778624400,
    "search_volume": 500,
    "score": 300,
    "related_queries": [
      "eurovision 2026 odds",
      "eurovision semi final 1"
    ],
    "category_ids": [
      4
    ],
    "entities": [
      {
        "id": 4587251481,
        "language": "en",
        "region": "US"
      },
      {
        "id": 4587251481,
        "language": "en",
        "region": "NO"
      }
    ],
    "normalized_keyword": "eurovision 2026 odds",
    "captured_at": "2026-05-13T06:23:03.872572+00:00"
  },
  {
    "keyword": "casper ruud",
    "region": "NO",
    "started_at_unix": 1778579400,
    "ended_at_unix": 1778589600,
    "search_volume": 1000,
    "score": 1000,
    "related_queries": [
      "casper ruud"
    ],
    "category_ids": [
      17
    ],
    "entities": [
      {
        "id": 4593821960,
        "language": "en",
        "region": "NO"
      },
      {
        "id": 4597170185,
        "language": "en",
        "region": "NO"
      },
      {
        "id": 4584968394,
        "language": "en",
        "region": "NO"
      },
      {
        "id": 4598239005,
        "language": "en",
        "region": "NO"
      },
      {
        "id": 4575227015,
        "language": "en",
        "region": "NO"
      }
    ],
    "normalized_keyword": "casper ruud",
    "captured_at": "2026-05-13T06:23:03.872572+00:00"
  },
  {
    "keyword": "grand prix 2026",
    "region": "NO",
    "started_at_unix": 1778617800,
    "ended_at_unix": 1778647200,
    "search_volume": 100,
    "score": 500,
    "related_queries": [
      "grand prix 2026"
    ],
    "category_ids": [
      17
    ],
    "entities": [
      {
        "id": 4588320596,
        "language": "en",
        "region": "NO"
      },
      {
        "id": 4593561942,
        "language": "en",
        "region": "NO"
      },
      {
        "id": 4579179172,
        "language": "en",
        "region": "NO"
      },
      {
        "id": 4592955444,
        "language": "en",
        "region": "NO"
      },
      {
        "id": 4565310167,
        "language": "en",
        "region": "NO"
      },
      {
        "id": 4558296920,
        "language": "en",
        "region": "NO"
      }
    ],
    "normalized_keyword": "grand prix 2026",
    "captured_at": "2026-05-13T06:23:03.872572+00:00"
  },
  {
    "keyword": "linda lampenius",
    "region": "NO",
    "started_at_unix": 1778616000,
    "ended_at_unix": 1778619600,
    "search_volume": 1000,
    "score": 1000,
    "related_queries": [
      "linda lampenius",
      "boy george eurovision",
      "eurovision odds"
    ],
    "category_ids": [
      4
    ],
    "entities": [
      {
        "id": 4597508139,
        "language": "en",
        "region": "NO"
      },
      {
        "id": 4589926623,
        "language": "en",
        "region": "NO"
      },
      {
        "id": 4597440378,
        "language": "en",
        "region": "NO"
      },
      {
        "id": 4586509688,
        "language": "en",
        "region": "NO"
      },
      {
        "id": 4587251481,
        "language": "en",
        "region": "NO"
      },
      {
        "id": 4597508139,
        "language": "en",
        "region": "US"
      },
      {
        "id": 4587251481,
        "language": "en",
        "region": "US"
      },
      {
        "id": 4596566581,
        "language": "en",
        "region": "US"
      },
      {
        "id": 4586509688,
        "language": "en",
        "region": "US"
      }
    ],
    "normalized_keyword": "linda lampenius",
    "captured_at": "2026-05-13T06:23:03.872572+00:00"
  },
  {
    "keyword": "dnb",
    "region": "NO",
    "started_at_unix": 1778645400,
    "ended_at_unix": 1778647200,
    "search_volume": 100,
    "score": 75,
    "related_queries": [
      "dnb"
    ],
    "category_ids": [
      11
    ],
    "entities": [
      {
        "id": 4581743604,
        "language": "de",
        "region": "NO"
      },
      {
        "id": 4597542680,
        "language": "de",
        "region": "NO"
      },
      {
        "id": 4594621664,
        "language": "de",
        "region": "NO"
      },
      {
        "id": 4596638002,
        "language": "de",
        "region": "NO"
      }
    ],
    "normalized_keyword": "dnb",
    "captured_at": "2026-05-13T06:23:03.872572+00:00"
  },
  {
    "keyword": "nrk",
    "region": "NO",
    "started_at_unix": 1778620200,
    "ended_at_unix": 1778622000,
    "search_volume": 1000,
    "score": 75,
    "related_queries": [
      "nrk",
      "nrk.no"
    ],
    "category_ids": [
      10
    ],
    "entities": [
      {
        "id": 4581890500,
        "language": "en",
        "region": "NO"
      },
      {
        "id": 4570074450,
        "language": "en",
        "region": "NO"
      },
      {
        "id": 4557661894,
        "language": "en",
        "region": "NO"
      },
      {
        "id": 4597690439,
        "language": "en",
        "region": "NO"
      },
      {
        "id": 4594364575,
        "language": "en",
        "region": "NO"
      },
      {
        "id": 4575589295,
        "language": "en",
        "region": "NO"
      },
      {
        "id": 4597353114,
        "language": "en",
        "region": "NO"
      },
      {
        "id": 4597931049,
        "language": "en",
        "region": "NO"
      },
      {
        "id": 4579421352,
        "language": "en",
        "region": "NO"
      },
      {
        "id": 4583836101,
        "language": "en",
        "region": "NO"
      },
      {
        "id": 4598106891,
        "language": "en",
        "region": "NO"
      },
      {
        "id": 4598743639,
        "language": "en",
        "region": "NO"
      },
      {
        "id": 4597134890,
        "language": "en",
        "region": "NO"
      },
      {
        "id": 4597728713,
        "language": "en",
        "region": "NO"
      },
      {
        "id": 4587832263,
        "language": "en",
        "region": "NO"
      }
    ],
    "normalized_keyword": "nrk",
    "captured_at": "2026-05-13T06:23:03.872572+00:00"
  },
  {
    "keyword": "moldova",
    "region": "NO",
    "started_at_unix": 1778613600,
    "ended_at_unix": 1778617800,
    "search_volume": 200,
    "score": 1000,
    "related_queries": [
      "moldova"
    ],
    "category_ids": [
      4
    ],
    "entities": [
      {
        "id": 4567432245,
        "language": "ro",
        "region": "NO"
      },
      {
        "id": 4596998809,
        "language": "ro",
        "region": "NO"
      },
      {
        "id": 4552524919,
        "language": "ro",
        "region": "NO"
      },
      {
        "id": 4595330708,
        "language": "ro",
        "region": "NO"
      },
      {
        "id": 4589150641,
        "language": "ro",
        "region": "NO"
      },
      {
        "id": 4598805999,
        "language": "ro",
        "region": "NO"
      },
      {
        "id": 4582129924,
        "language": "ro",
        "region": "NO"
      },
      {
        "id": 4586762777,
        "language": "ro",
        "region": "NO"
      },
      {
        "id": 4591618446,
        "language": "ro",
        "region": "NO"
      },
      {
        "id": 4597103219,
        "language": "ro",
        "region": "NO"
      },
      {
        "id": 4597356982,
        "language": "ro",
        "region": "NO"
      },
      {
        "id": 4589620801,
        "language": "ro",
        "region": "NO"
      }
    ],
    "normalized_keyword": "moldova",
    "captured_at": "2026-05-13T06:23:03.872572+00:00"
  },
  {
    "keyword": "eurojackpot",
    "region": "NO",
    "started_at_unix": 1778615400,
    "ended_at_unix": 1778647200,
    "search_volume": 200,
    "score": 100,
    "related_queries": [
      "eurojackpot"
    ],
    "category_ids": [
      6
    ],
    "entities": [
      {
        "id": 4580771647,
        "language": "en",
        "region": "NO"
      }
    ],
    "normalized_keyword": "eurojackpot",
    "captured_at": "2026-05-13T06:23:03.872572+00:00"
  },
  {
    "keyword": "montenegro",
    "region": "NO",
    "started_at_unix": 1778615400,
    "ended_at_unix": 1778619600,
    "search_volume": 200,
    "score": 1000,
    "related_queries": [
      "montenegro"
    ],
    "category_ids": [
      10
    ],
    "entities": [
      {
        "id": 4591975104,
        "language": "en",
        "region": "NO"
      },
      {
        "id": 4584111889,
        "language": "en",
        "region": "NO"
      },
      {
        "id": 4582803582,
        "language": "en",
        "region": "NO"
      },
      {
        "id": 4563983526,
        "language": "en",
        "region": "NO"
      },
      {
        "id": 4594750112,
        "language": "en",
        "region": "NO"
      },
      {
        "id": 4548365241,
        "language": "en",
        "region": "NO"
      },
      {
        "id": 4555531816,
        "language": "en",
        "region": "NO"
      }
    ],
    "normalized_keyword": "montenegro",
    "captured_at": "2026-05-13T06:23:03.872572+00:00"
  },
  {
    "keyword": "odd reitan",
    "region": "NO",
    "started_at_unix": 1778611800,
    "ended_at_unix": 1778616600,
    "search_volume": 200,
    "score": 500,
    "related_queries": [
      "odd reitan"
    ],
    "category_ids": [
      17
    ],
    "entities": [
      {
        "id": 4593123050,
        "language": "en",
        "region": "NO"
      },
      {
        "id": 4587659261,
        "language": "en",
        "region": "NO"
      }
    ],
    "normalized_keyword": "odd reitan",
    "captured_at": "2026-05-13T06:23:03.872572+00:00"
  },
  {
    "keyword": "southampton mot middlesbrough",
    "region": "NO",
    "started_at_unix": 1778613000,
    "ended_at_unix": 1778616600,
    "search_volume": 200,
    "score": 1000,
    "related_queries": [
      "southampton mot middlesbrough"
    ],
    "category_ids": [
      17
    ],
    "entities": [
      {
        "id": 4587832263,
        "language": "en",
        "region": "NO"
      }
    ],
    "normalized_keyword": "southampton mot middlesbrough",
    "captured_at": "2026-05-13T06:23:03.872572+00:00"
  },
  {
    "keyword": "tyskland",
    "region": "NO",
    "started_at_unix": 1778577600,
    "ended_at_unix": 1778581800,
    "search_volume": 200,
    "score": 1000,
    "related_queries": [
      "tyskland"
    ],
    "category_ids": [
      10
    ],
    "entities": [
      {
        "id": 4595563627,
        "language": "en",
        "region": "NO"
      },
      {
        "id": 4596608240,
        "language": "en",
        "region": "NO"
      },
      {
        "id": 4597134890,
        "language": "en",
        "region": "NO"
      },
      {
        "id": 4593203182,
        "language": "en",
        "region": "NO"
      },
      {
        "id": 4592489922,
        "language": "en",
        "region": "NO"
      },
      {
        "id": 4592221775,
        "language": "en",
        "region": "NO"
      },
      {
        "id": 4592221860,
        "language": "en",
        "region": "NO"
      },
      {
        "id": 4594199866,
        "language": "en",
        "region": "NO"
      }
    ],
    "normalized_keyword": "tyskland",
    "captured_at": "2026-05-13T06:23:03.872572+00:00"
  },
  {
    "keyword": "nrk nyheter",
    "region": "NO",
    "started_at_unix": 1778621400,
    "ended_at_unix": 1778624400,
    "search_volume": 200,
    "score": 100,
    "related_queries": [
      "nrk nyheter"
    ],
    "category_ids": [
      11
    ],
    "entities": [
      {
        "id": 4595294717,
        "language": "no",
        "region": "NO"
      },
      {
        "id": 4547497637,
        "language": "no",
        "region": "NO"
      }
    ],
    "normalized_keyword": "nrk nyheter",
    "captured_at": "2026-05-13T06:23:03.872572+00:00"
  },
  {
    "keyword": "georgia",
    "region": "NO",
    "started_at_unix": 1778615400,
    "ended_at_unix": 1778618400,
    "search_volume": 100,
    "score": 900,
    "related_queries": [
      "georgia"
    ],
    "category_ids": [
      6
    ],
    "entities": [
      {
        "id": 4583644994,
        "language": "en",
        "region": "NO"
      },
      {
        "id": 4597428866,
        "language": "en",
        "region": "NO"
      },
      {
        "id": 4598675691,
        "language": "en",
        "region": "NO"
      },
      {
        "id": 4596914372,
        "language": "en",
        "region": "NO"
      },
      {
        "id": 4597916635,
        "language": "en",
        "region": "NO"
      },
      {
        "id": 4596042179,
        "language": "en",
        "region": "NO"
      },
      {
        "id": 4595557090,
        "language": "en",
        "region": "NO"
      },
      {
        "id": 4597964697,
        "language": "en",
        "region": "NO"
      }
    ],
    "normalized_keyword": "georgia",
    "captured_at": "2026-05-13T06:23:03.872572+00:00"
  },
  {
    "keyword": "sergio ramos",
    "region": "NO",
    "started_at_unix": 1778593800,
    "ended_at_unix": 1778599200,
    "search_volume": 100,
    "score": 1000,
    "related_queries": [
      "sergio ramos"
    ],
    "category_ids": [
      17
    ],
    "entities": [
      {
        "id": 4575295179,
        "language": "es",
        "region": "NO"
      }
    ],
    "normalized_keyword": "sergio ramos",
    "captured_at": "2026-05-13T06:23:03.872572+00:00"
  },
  {
    "keyword": "yukos",
    "region": "NO",
    "started_at_unix": 1778595000,
    "ended_at_unix": 1778600400,
    "search_volume": 100,
    "score": 1000,
    "related_queries": [
      "yukos"
    ],
    "category_ids": [
      10
    ],
    "entities": [
      {
        "id": 4596867926,
        "language": "en",
        "region": "NO"
      }
    ],
    "normalized_keyword": "yukos",
    "captured_at": "2026-05-13T06:23:03.872572+00:00"
  },
  {
    "keyword": "tv guide",
    "region": "NO",
    "started_at_unix": 1778609400,
    "ended_at_unix": 1778611200,
    "search_volume": 200,
    "score": 50,
    "related_queries": [
      "tv guide"
    ],
    "category_ids": [
      4
    ],
    "entities": [
      {
        "id": 4595205108,
        "language": "en",
        "region": "US"
      },
      {
        "id": 4597162147,
        "language": "en",
        "region": "US"
      },
      {
        "id": 4598294354,
        "language": "en",
        "region": "US"
      },
      {
        "id": 4592517766,
        "language": "en",
        "region": "US"
      },
      {
        "id": 4590138242,
        "language": "en",
        "region": "US"
      },
      {
        "id": 4576213277,
        "language": "en",
        "region": "US"
      },
      {
        "id": 4585224554,
        "language": "en",
        "region": "US"
      },
      {
        "id": 4583096757,
        "language": "en",
        "region": "US"
      }
    ],
    "normalized_keyword": "tv guide",
    "captured_at": "2026-05-13T06:23:03.872572+00:00"
  }
]